{
  "id": "mock-exam-2",
  "title": "Mock Exam 2",
  "description": "25 multiple choice + 6 written · 50 min",
  "questions": [
    {
      "id": "q1",
      "number": 1,
      "type": "multiple_choice",
      "text": "Choose the most appropriate title for the passage.",
      "context": "People often assume that accurate predictions depend mainly on experience. However, studies of forecasting show that experts sometimes become overly committed to their original expectations. When new evidence appears, they may unconsciously interpret it in ways that support their previous beliefs. Individuals who regularly reconsider their conclusions, by contrast, are often more successful because they adjust their judgments whenever reliable evidence changes.",
      "options": [
        {
          "id": "1",
          "text": "Experience Always Produces Accurate Predictions"
        },
        {
          "id": "2",
          "text": "Why Changing Your Mind Can Improve Judgement"
        },
        {
          "id": "3",
          "text": "The Importance of Trusting First Impressions"
        },
        {
          "id": "4",
          "text": "Why Experts Never Make Prediction Errors"
        },
        {
          "id": "5",
          "text": "How Knowledge Eliminates Uncertainty"
        }
      ]
    },
    {
      "id": "q2",
      "number": 2,
      "type": "multiple_choice",
      "text": "Choose the most appropriate topic of the passage.",
      "context": "Throughout history, many discoveries have resulted from unexpected observations rather than careful planning alone. Scientists occasionally notice results that differ from their predictions and choose to investigate them instead of dismissing them as mistakes. Although chance may provide the initial observation, important discoveries usually occur because researchers recognise the significance of unusual evidence and examine it systematically.",
      "options": [
        {
          "id": "1",
          "text": "the dangers of scientific experiments"
        },
        {
          "id": "2",
          "text": "how unexpected observations contribute to scientific discovery"
        },
        {
          "id": "3",
          "text": "the history of laboratory equipment"
        },
        {
          "id": "4",
          "text": "why experiments should always follow predictions exactly"
        },
        {
          "id": "5",
          "text": "methods of reducing research costs"
        }
      ]
    },
    {
      "id": "q3",
      "number": 3,
      "type": "multiple_choice",
      "text": "Which statement is supported by the passage?",
      "options": [
        {
          "id": "1",
          "text": "Scientific discoveries occur only by accident."
        },
        {
          "id": "2",
          "text": "Researchers should ignore unexpected observations."
        },
        {
          "id": "3",
          "text": "Unusual results may lead to important discoveries if they are investigated carefully."
        },
        {
          "id": "4",
          "text": "Scientists rarely change their original hypotheses."
        },
        {
          "id": "5",
          "text": "Careful planning prevents unexpected findings."
        }
      ]
    },
    {
      "id": "q4",
      "number": 4,
      "type": "multiple_choice",
      "text": "Choose the main idea of the passage.",
      "context": "Many people believe that successful communication depends primarily on speaking clearly. Communication researchers, however, argue that effective listening is equally important. Individuals who ask questions, confirm understanding, and consider another person's perspective are less likely to misunderstand complex information. As a result, successful communication requires active participation from both speakers and listeners.",
      "options": [
        {
          "id": "1",
          "text": "Speaking is more important than listening."
        },
        {
          "id": "2",
          "text": "Effective communication depends on active listening as well as clear speaking."
        },
        {
          "id": "3",
          "text": "Questions usually create misunderstandings."
        },
        {
          "id": "4",
          "text": "People should avoid discussing complicated topics."
        },
        {
          "id": "5",
          "text": "Listening carefully always eliminates disagreement."
        }
      ]
    },
    {
      "id": "q5",
      "number": 5,
      "type": "multiple_choice",
      "text": "How many of the following statements are NOT consistent with the passage?",
      "context": "A university student wanted to improve her writing skills. Instead of submitting only final drafts, she began asking classmates for feedback before completing each essay. Although receiving criticism was sometimes uncomfortable, she gradually recognised recurring weaknesses and learned how to correct them. Over time, the quality of her writing improved noticeably.\n\nStatements\n\n(a) She asked for suggestions before finishing her essays.\n(b) Feedback was always enjoyable for her.\n(c) She discovered repeated weaknesses in her writing.\n(d) Her writing improved after using feedback.\n(e) She refused to change her writing.\n(f) Constructive criticism can contribute to improvement.",
      "options": [
        {
          "id": "1",
          "text": "1"
        },
        {
          "id": "2",
          "text": "2"
        },
        {
          "id": "3",
          "text": "3"
        },
        {
          "id": "4",
          "text": "4"
        },
        {
          "id": "5",
          "text": "5"
        }
      ]
    },
    {
      "id": "q6",
      "number": 6,
      "type": "multiple_choice",
      "text": "How many of the following vocabulary pairs are correctly matched?",
      "context": "(a) consistent — remaining the same\n(b) scarce — abundant\n(c) interpret — explain the meaning of\n(d) efficient — producing good results with little waste\n(e) rigid — flexible\n(f) justify — provide a good reason for\n(g) diminish — become smaller\n(h) temporary — permanent\n(i) verify — confirm the truth of\n(j) infer — reach a conclusion from evidence",
      "options": [
        {
          "id": "1",
          "text": "5"
        },
        {
          "id": "2",
          "text": "6"
        },
        {
          "id": "3",
          "text": "7"
        },
        {
          "id": "4",
          "text": "8"
        },
        {
          "id": "5",
          "text": "9"
        }
      ]
    },
    {
      "id": "q7",
      "number": 7,
      "type": "multiple_choice",
      "text": "Which statement does NOT agree with the two explanations given in the passage?",
      "context": "Some researchers argue that cities become centres of innovation because they bring together large numbers of talented individuals who exchange ideas easily. Others believe that innovation depends more on access to financial resources, educational institutions, and supportive government policies. Although these explanations focus on different factors, both attempt to explain why certain cities produce more inventions than others.",
      "options": [
        {
          "id": "1",
          "text": "Large populations may encourage the exchange of ideas."
        },
        {
          "id": "2",
          "text": "Financial support can influence innovation."
        },
        {
          "id": "3",
          "text": "Educational institutions may contribute to technological development."
        },
        {
          "id": "4",
          "text": "Only population size determines whether innovation occurs."
        },
        {
          "id": "5",
          "text": "The two explanations propose different causes for the same pattern."
        }
      ]
    },
    {
      "id": "q8",
      "number": 8,
      "type": "multiple_choice",
      "text": "Which underlined word is used incorrectly?",
      "options": [
        {
          "id": "1",
          "text": "The committee reached a _compromise_ after lengthy negotiations."
        },
        {
          "id": "2",
          "text": "Researchers carefully _evaluated_ the evidence."
        },
        {
          "id": "3",
          "text": "The company decided to _expand_ its international operations."
        },
        {
          "id": "4",
          "text": "The engineer designed the building to remain _unstable_ during earthquakes."
        },
        {
          "id": "5",
          "text": "Historians continue to _analyse_ ancient manuscripts."
        }
      ]
    },
    {
      "id": "q9",
      "number": 9,
      "type": "multiple_choice",
      "text": "Which meaning best matches the underlined expression?",
      "context": "People who demonstrate _critical thinking_ evaluate evidence carefully before reaching conclusions. They compare different explanations, recognise weak arguments, and remain willing to change their opinions if stronger evidence becomes available.",
      "options": [
        {
          "id": "1",
          "text": "accepting information without questioning it"
        },
        {
          "id": "2",
          "text": "evaluating information carefully before making judgments"
        },
        {
          "id": "3",
          "text": "remembering facts very quickly"
        },
        {
          "id": "4",
          "text": "solving mathematical problems mentally"
        },
        {
          "id": "5",
          "text": "avoiding difficult decisions"
        }
      ]
    },
    {
      "id": "q10",
      "number": 10,
      "type": "multiple_choice",
      "text": "Which underlined word is NOT appropriate in context?",
      "context": "Successful investigations require researchers to collect accurate data, examine alternative explanations, and report their findings honestly. Scientists must remain ① _objective_ throughout the research process and avoid allowing personal opinions to influence their conclusions. Publishing misleading information would therefore be ② _ethical_ rather than scientific. Reliable research depends upon ③ _careful_ observation, ④ _systematic_ analysis, and ⑤ _independent_ verification.",
      "options": [
        {
          "id": "1",
          "text": "objective"
        },
        {
          "id": "2",
          "text": "ethical"
        },
        {
          "id": "3",
          "text": "careful"
        },
        {
          "id": "4",
          "text": "systematic"
        },
        {
          "id": "5",
          "text": "independent"
        }
      ]
    },
    {
      "id": "q11",
      "number": 11,
      "type": "multiple_choice",
      "text": "Choose the word that best completes the blank.",
      "context": "Students often believe that making mistakes indicates failure. Educational psychologists, however, argue that errors become valuable learning opportunities when students examine them carefully and modify their study methods. Reflection is therefore an ________ part of effective learning.",
      "options": [
        {
          "id": "1",
          "text": "accidental"
        },
        {
          "id": "2",
          "text": "essential"
        },
        {
          "id": "3",
          "text": "temporary"
        },
        {
          "id": "4",
          "text": "irrelevant"
        },
        {
          "id": "5",
          "text": "cautious"
        }
      ]
    },
    {
      "id": "q12",
      "number": 12,
      "type": "multiple_choice",
      "text": "Which sentence best fits the blank?",
      "context": "Experienced musicians rarely become satisfied with simply repeating pieces they already perform well. Instead, they identify passages that remain difficult and practise those sections repeatedly until they improve. ______\n\nConsequently, their performance continues to develop over many years.",
      "options": [
        {
          "id": "1",
          "text": "Deliberately practising weaknesses is more effective than repeating strengths."
        },
        {
          "id": "2",
          "text": "Skilled musicians never make mistakes."
        },
        {
          "id": "3",
          "text": "Practice becomes unnecessary after professional success."
        },
        {
          "id": "4",
          "text": "Talent develops independently of effort."
        },
        {
          "id": "5",
          "text": "Difficult practice usually reduces confidence without improving performance."
        }
      ]
    },
    {
      "id": "q13",
      "number": 13,
      "type": "multiple_choice",
      "text": "Choose the most appropriate order of the following sentences.",
      "context": "(A) After comparing several explanations, they identified the factor responsible for the unexpected result.\n\n(B) Researchers noticed that one experiment produced results that differed from previous studies.\n\n(C) Rather than ignoring the difference, they repeated the experiment using additional controls.",
      "options": [
        {
          "id": "1",
          "text": "(B) → (C) → (A)"
        },
        {
          "id": "2",
          "text": "(A) → (B) → (C)"
        },
        {
          "id": "3",
          "text": "(C) → (A) → (B)"
        },
        {
          "id": "4",
          "text": "(B) → (A) → (C)"
        },
        {
          "id": "5",
          "text": "(C) → (B) → (A)"
        }
      ]
    },
    {
      "id": "q14",
      "number": 14,
      "type": "multiple_choice",
      "text": "Choose the sentence that does NOT belong.",
      "context": "Scientific research depends on careful observation and honest reporting.",
      "options": [
        {
          "id": "1",
          "text": "Researchers should record results accurately."
        },
        {
          "id": "2",
          "text": "Independent verification increases reliability."
        },
        {
          "id": "3",
          "text": "Careful experiments reduce the risk of error."
        },
        {
          "id": "4",
          "text": "Ancient castles were often surrounded by defensive walls."
        },
        {
          "id": "5",
          "text": "Reliable evidence strengthens scientific conclusions."
        }
      ]
    },
    {
      "id": "q15",
      "number": 15,
      "type": "multiple_choice",
      "text": "Choose the most appropriate word for the blank.",
      "context": "Effective teams recognise that disagreement can improve decision-making when it is expressed respectfully. Members who question assumptions often identify problems before they become serious. Constructive discussion therefore promotes ________ rather than conflict.",
      "options": [
        {
          "id": "1",
          "text": "cooperation"
        },
        {
          "id": "2",
          "text": "isolation"
        },
        {
          "id": "3",
          "text": "prejudice"
        },
        {
          "id": "4",
          "text": "confusion"
        },
        {
          "id": "5",
          "text": "hesitation"
        }
      ]
    },
    {
      "id": "q16",
      "number": 16,
      "type": "multiple_choice",
      "text": "Which statement is supported by the passage?",
      "context": "Researchers studying sleep have found that memory is strengthened not only while people are awake but also during sleep. During certain stages of sleep, the brain reorganises recently learned information, making it easier to remember later. Although sleeping cannot replace studying, adequate rest significantly improves learning efficiency.",
      "options": [
        {
          "id": "1",
          "text": "Sleeping completely replaces studying."
        },
        {
          "id": "2",
          "text": "Memory can improve while people are asleep."
        },
        {
          "id": "3",
          "text": "Only long hours of studying improve memory."
        },
        {
          "id": "4",
          "text": "Sleep has little effect on learning."
        },
        {
          "id": "5",
          "text": "Researchers no longer study sleep."
        }
      ]
    },
    {
      "id": "q17",
      "number": 17,
      "type": "multiple_choice",
      "text": "Choose the most appropriate title for the passage.",
      "context": "People often believe that successful habits depend mainly on self-discipline. Behavioural scientists, however, have shown that small environmental changes can make desirable behaviours easier to perform. Placing healthy food where it is visible, preparing exercise clothes in advance, or reducing distractions while studying all increase the likelihood that positive habits will continue.",
      "options": [
        {
          "id": "1",
          "text": "Why Self-Discipline Is Unnecessary"
        },
        {
          "id": "2",
          "text": "How Small Environmental Changes Encourage Good Habits"
        },
        {
          "id": "3",
          "text": "The History of Healthy Living"
        },
        {
          "id": "4",
          "text": "Why Successful People Never Face Temptation"
        },
        {
          "id": "5",
          "text": "The Relationship Between Intelligence and Habit Formation"
        }
      ]
    },
    {
      "id": "q18",
      "number": 18,
      "type": "multiple_choice",
      "text": "Choose the word that best completes the blank.",
      "context": "The museum decided to restore the damaged painting immediately because exposure to moisture would have caused the damage to become even more ________.",
      "options": [
        {
          "id": "1",
          "text": "severe"
        },
        {
          "id": "2",
          "text": "ordinary"
        },
        {
          "id": "3",
          "text": "temporary"
        },
        {
          "id": "4",
          "text": "unnecessary"
        },
        {
          "id": "5",
          "text": "predictable"
        }
      ]
    },
    {
      "id": "q19",
      "number": 19,
      "type": "multiple_choice",
      "text": "Which sentence best summarises the passage?",
      "context": "Economic systems consist of many interconnected relationships among consumers, businesses, governments, and financial institutions. Changes affecting one group frequently influence others in unexpected ways. As a result, economists often analyse the entire system instead of focusing on individual factors alone.",
      "options": [
        {
          "id": "1",
          "text": "Economic systems rarely change."
        },
        {
          "id": "2",
          "text": "Modern economies are interconnected, so individual changes may affect many different groups."
        },
        {
          "id": "3",
          "text": "Governments completely control every economy."
        },
        {
          "id": "4",
          "text": "Businesses always benefit from economic change."
        },
        {
          "id": "5",
          "text": "Consumers have little influence on economic activity."
        }
      ]
    },
    {
      "id": "q20",
      "number": 20,
      "type": "multiple_choice",
      "text": "Choose the word that best completes the passage.",
      "context": "Researchers frequently revise their conclusions after collecting additional information. Rather than viewing revision as failure, scientists consider it evidence that the research process is working effectively. Scientific knowledge therefore continues to ________ as new evidence becomes available.",
      "options": [
        {
          "id": "1",
          "text": "disappear"
        },
        {
          "id": "2",
          "text": "evolve"
        },
        {
          "id": "3",
          "text": "weaken"
        },
        {
          "id": "4",
          "text": "hesitate"
        },
        {
          "id": "5",
          "text": "simplify"
        }
      ]
    },
    {
      "id": "q21",
      "number": 21,
      "type": "multiple_choice",
      "text": "Choose the most appropriate sentence to fill the blank.",
      "context": "People often believe that confidence automatically produces success. However, psychologists have found that confidence alone is rarely enough. Successful individuals regularly evaluate their performance, identify weaknesses, and adjust their strategies accordingly. ______",
      "options": [
        {
          "id": "1",
          "text": "Continuous improvement depends on honest self-evaluation."
        },
        {
          "id": "2",
          "text": "Confidence always guarantees success."
        },
        {
          "id": "3",
          "text": "Mistakes should be ignored whenever possible."
        },
        {
          "id": "4",
          "text": "Talented people rarely need feedback."
        },
        {
          "id": "5",
          "text": "Successful people avoid changing their methods."
        }
      ]
    },
    {
      "id": "q22",
      "number": 22,
      "type": "multiple_choice",
      "text": "Choose the most appropriate order of the following paragraphs.",
      "context": "(A) They then tested a new explanation using additional experiments.\n\n(B) Scientists noticed that the existing theory could not explain recent observations.\n\n(C) The revised theory successfully accounted for both the original and the new evidence.",
      "options": [
        {
          "id": "1",
          "text": "(B) → (A) → (C)"
        },
        {
          "id": "2",
          "text": "(A) → (B) → (C)"
        },
        {
          "id": "3",
          "text": "(C) → (A) → (B)"
        },
        {
          "id": "4",
          "text": "(B) → (C) → (A)"
        },
        {
          "id": "5",
          "text": "(A) → (C) → (B)"
        }
      ]
    },
    {
      "id": "q23",
      "number": 23,
      "type": "multiple_choice",
      "text": "Which statement is NOT supported by the passage?",
      "context": "Studies suggest that neighbourhoods with strong social connections are often safer because residents communicate regularly and are more willing to report suspicious activity or assist one another. Researchers argue that cooperation strengthens communities even before problems arise.",
      "options": [
        {
          "id": "1",
          "text": "Social cooperation may improve neighbourhood safety."
        },
        {
          "id": "2",
          "text": "Communication encourages cooperation."
        },
        {
          "id": "3",
          "text": "Strong communities often help prevent problems."
        },
        {
          "id": "4",
          "text": "Community cooperation becomes valuable only after crime occurs."
        },
        {
          "id": "5",
          "text": "Residents who know one another are often more willing to help."
        }
      ]
    },
    {
      "id": "q24",
      "number": 24,
      "type": "multiple_choice",
      "text": "Choose the word that best completes the passage.",
      "context": "Because technology changes rapidly, employees are expected to update their knowledge throughout their careers. Employers therefore increasingly value people who demonstrate curiosity, flexibility, and a willingness to continue ________.",
      "options": [
        {
          "id": "1",
          "text": "learning"
        },
        {
          "id": "2",
          "text": "retiring"
        },
        {
          "id": "3",
          "text": "complaining"
        },
        {
          "id": "4",
          "text": "delaying"
        },
        {
          "id": "5",
          "text": "competing"
        }
      ]
    },
    {
      "id": "q25",
      "number": 25,
      "type": "multiple_choice",
      "text": "Choose the most appropriate title for the passage.",
      "context": "Many organisations encourage employees to discuss unsuccessful projects openly. Rather than assigning blame, managers analyse what happened and identify ways to improve future planning. This approach helps organisations avoid repeating mistakes while encouraging innovation and continuous improvement.",
      "options": [
        {
          "id": "1",
          "text": "Learning from Organisational Mistakes"
        },
        {
          "id": "2",
          "text": "Why Successful Companies Never Experience Failure"
        },
        {
          "id": "3",
          "text": "Technology Prevents Human Error"
        },
        {
          "id": "4",
          "text": "The Importance of Strict Rules"
        },
        {
          "id": "5",
          "text": "Competition Is the Only Key to Success"
        }
      ]
    },
    {
      "id": "q26",
      "number": 26,
      "type": "fill_blank",
      "text": "Complete the summary using the words from the box.",
      "context": "**Word Box: feedback · evidence · confidence · revise · assumptions**\n\nPeople sometimes become overly (A) __________ in their own opinions. As a result, they may ignore new (B) __________ that contradicts their previous (C) __________. Successful thinkers instead seek (D) __________ from others and remain willing to (E) __________ their conclusions when necessary."
    },
    {
      "id": "q27",
      "number": 27,
      "type": "multiple_choice",
      "text": "Choose the word that is closest in meaning to the underlined word.",
      "context": "The company decided to _modify_ its marketing strategy after reviewing customer feedback.",
      "options": [
        {
          "id": "1",
          "text": "preserve"
        },
        {
          "id": "2",
          "text": "change"
        },
        {
          "id": "3",
          "text": "abandon"
        },
        {
          "id": "4",
          "text": "ignore"
        },
        {
          "id": "5",
          "text": "discover"
        }
      ]
    },
    {
      "id": "q28",
      "number": 28,
      "type": "written",
      "text": "Arrange the following words and phrases into one grammatically correct sentence.",
      "context": "Arrange all of the following words and phrases into one complete sentence. You may not change the form of any word.\n\n(the more / students / reflect on / their mistakes / the more / they / improve / their understanding)",
      "placeholder": "Write the complete sentence here..."
    },
    {
      "id": "q29",
      "number": 29,
      "type": "multiple_choice",
      "text": "Choose the grammatically correct sentence.",
      "options": [
        {
          "id": "1",
          "text": "Not until the report was published did the public understand the problem."
        },
        {
          "id": "2",
          "text": "Not until the report was published the public did understand the problem."
        },
        {
          "id": "3",
          "text": "Not until did the report was published the public understand the problem."
        },
        {
          "id": "4",
          "text": "Not until the report published did the public understood the problem."
        },
        {
          "id": "5",
          "text": "Not until the report was published the public understood the problem."
        }
      ]
    },
    {
      "id": "q30",
      "number": 30,
      "type": "written_multi",
      "text": "Complete both tasks below.",
      "context": "Task 4.1 — Rewrite the sentence using the word given.\n\nWord: despite\n\nAlthough the engineer encountered several unexpected problems, she completed the project successfully.\n\nTask 4.2 — Arrange all of the following words and phrases into one complete sentence. You may not change the form of any word.\n\n(only after / had / carefully / the researchers / analysed / the data / did / they / reach / their conclusion)",
      "subQuestions": [
        {
          "label": "4.1",
          "placeholder": "Write the rewritten sentence here..."
        },
        {
          "label": "4.2",
          "placeholder": "Write the complete sentence here..."
        }
      ]
    },
    {
      "id": "q31",
      "number": 31,
      "type": "written",
      "text": "Write 2–3 English sentences answering the following question.\n\nSeveral passages in this exam suggest that people improve by examining mistakes, accepting feedback, and changing their ideas.\n\nDo you agree?\n\nSupport your answer using one idea from the passages and one example from your own experience.",
      "placeholder": "Write your answer here (2–3 sentences)..."
    }
  ]
}